secursus_api/__init__.py
secursus_api/api.py
secursus_api-1.0.2.dist-info/LICENSE
secursus_api-1.0.2.dist-info/METADATA
secursus_api-1.0.2.dist-info/WHEEL
secursus_api-1.0.2.dist-info/top_level.txt
secursus_api-1.0.2.dist-info/RECORD
