Metadata-Version: 2.1
Name: secursus-api
Version: 1.0.2
Summary: Library PiP for Secursus api.
Home-page: https://gitlab.com/secursus_public/secursus_pip
Author: BRISSON Pierre-Alain
Author-email: pab@secursus.com
License: UNKNOWN
Platform: UNKNOWN
Classifier: Programming Language :: Python :: 3
Classifier: License :: OSI Approved :: MIT License
Classifier: Operating System :: OS Independent
Requires-Python: >=3.6
